<extension xmlns="http://ns.adobe.com/air/extension/4.0">
	<id>com.growthpush.ane</id>
	<versionNumber>1.0.0</versionNumber>
	<name>
		<text xml:lang="en_US">Growth Push</text>
	</name>
	<platforms>
		<platform name="Android-ARM">
			<applicationDeployment>
				<nativeLibrary>growthpushane.jar</nativeLibrary>
				<initializer>com.growthpush.ane.GrowthPushExtension</initializer>
				<finalizer>com.growthpush.ane.GrowthPushExtension</finalizer>
			</applicationDeployment>
		</platform>
		<platform name="iPhone-ARM">
			<applicationDeployment>
				<nativeLibrary>libGrowthPushANE.a</nativeLibrary>
				<initializer>GPAneExtInitializer</initializer>
				<finalizer>GPAneExtFinalizer</finalizer>
			</applicationDeployment>
		</platform>
		<platform name="default">
			<applicationDeployment />
		</platform>
	</platforms>
</extension>